README.txt
buildout.cfg
setup.py
aws/__init__.py
aws.inlineuserpref.egg-info/PKG-INFO
aws.inlineuserpref.egg-info/SOURCES.txt
aws.inlineuserpref.egg-info/dependency_links.txt
aws.inlineuserpref.egg-info/entry_points.txt
aws.inlineuserpref.egg-info/namespace_packages.txt
aws.inlineuserpref.egg-info/not-zip-safe
aws.inlineuserpref.egg-info/requires.txt
aws.inlineuserpref.egg-info/top_level.txt
aws/inlineuserpref/__init__.py
aws/inlineuserpref/atkssfields.py
aws/inlineuserpref/configure.zcml
aws/inlineuserpref/controlpanel.py
aws/inlineuserpref/interfaces.py
aws/inlineuserpref/overrides.zcml
aws/inlineuserpref/tests.py
aws/inlineuserpref/version.txt
aws/inlineuserpref/locales/README.txt
aws/inlineuserpref/locales/aws.inlineuserpref.pot
aws/inlineuserpref/locales/updatelocales.py
aws/inlineuserpref/locales/fr/LC_MESSAGES/aws.inlineuserpref.mo
aws/inlineuserpref/locales/fr/LC_MESSAGES/aws.inlineuserpref.po
aws/inlineuserpref/profiles/default/actionicons.xml
aws/inlineuserpref/profiles/default/browserlayer.xml
aws/inlineuserpref/profiles/default/controlpanel.xml
aws/inlineuserpref/profiles/default/memberdata_properties.xml
aws/inlineuserpref/profiles/default/metadata.xml
docs/HISTORY.txt
docs/LICENSE.txt