Metadata-Version: 1.0
Name: aws.inlineuserpref
Version: 1.0.0
Summary: Per user Plone inline KSS editing preference
Home-page: http://plone.org/products/aws-inlineuserpref
Author: Gilles Lenfant
Author-email: gilles.lenfant@ingeniweb.com
License: GPL
Keywords: plone kss preferences
Platform: UNKNOWN
Classifier: Framework :: Plone
Classifier: Programming Language :: Python
Classifier: Topic :: Software Development :: Libraries :: Python Modules
Classifier: Development Status :: 5 - Production/Stable
